Serial Adder/serial_adder.v
`timescale 1ns / 1ps 
module serial_adder
#(parameter bit = 4 )
(
    input clk , ctrl , // //Control Signal for Registers A & B and reset_n for D Flip flop
    input [bit-1:0]I_A , I_B , //Parallel Loads for Registers A and B 
    output [bit-1:0]result 
);
//Storage Elements 
reg [bit-1:0]Q_reg_A , Q_next_A , Q_reg_B , Q_next_B ;
reg Q_next_D , Q_reg_D ,sum , carry_out;
always @(posedge clk , negedge ctrl)
begin
    Q_reg_A <= Q_next_A ;
    Q_reg_B <= Q_next_B ;
    if(!ctrl)
        Q_reg_D <= 1'b0;
    else
        Q_reg_D <= Q_next_D ;
end
//Next state Logic 
always @(*)
begin
    {carry_out , sum} = Q_reg_A[0] + Q_reg_B[0] + Q_reg_D ;
    Q_next_D = carry_out ;
    Q_next_A = ctrl ? { sum , Q_reg_A[bit-1:1]} : I_A ;
    Q_next_B = ctrl ? {1'b0 , Q_reg_B[bit-1:1]} : I_B ;
    
end
//Output Logic
assign result = Q_reg_A   ;
endmodule

Serial Adder/serial_adder_tb.v
`timescale 1ns / 1ps
module serial_adder_tb();
//declare the local reg and wire identifiers 
localparam  bit = 4 ;
reg clk ,ctrl ;
reg [bit-1:0] I_A , I_B ;
wire [bit-1:0]result;
//Create the dumpfile and dumpvars to generate the waves 
initial
begin
    $dumpfile("serial_adder_tb.vcd");
    $dumpvars(0,serial_adder_tb);
end
//instantiate the unit under test
serial_adder #(.bit(bit)) uut
(
    .clk(clk),
    .I_A(I_A),
    .I_B(I_B),
    .ctrl(ctrl),
    .result(result)
);
//Generate the clock 
localparam T = 20 ;
always 
begin
    clk = 1'b0 ;
    #(T/2);
    clk = 1'b1 ;
    #(T/2); 
end
// create the stimlu to simulate the uut 
initial 
begin
    I_A = 'd4 ;
    I_B = 'd6 ;
    ctrl = 1'b0 ;
    @(posedge clk) ctrl = 1'b1 ;
    repeat(bit) @(posedge clk);
    ctrl = 1'b0 ;
    I_A = 'd14 ;
    I_B = 'd7 ;
    @(posedge clk) ctrl = 1'b1 ;
    ctrl = 1'b1 ;
    repeat(bit+1) @(posedge clk) ;
    ctrl = 1'b0 ;
    I_A = 'd9 ;
    I_B = 'd6 ;
    @(posedge clk) ctrl = 1'b1 ;
    ctrl = 1'b1 ;
    repeat(bit+1) @(posedge clk) ;
    $finish ;
end
endmodule

Serial Adder/serial_adder_tb.vcd
$date
	Sat Jul 05 16:06:00 2025
$end
$version
	Icarus Verilog
$end
$timescale
	1ps
$end
$scope module serial_adder_tb $end
$var wire 4 ! result [3:0] $end
$var parameter 32 " T $end
$var parameter 32 # bit $end
$var reg 4 $ I_A [3:0] $end
$var reg 4 % I_B [3:0] $end
$var reg 1 & clk $end
$var reg 1 ' ctrl $end
$scope module uut $end
$var wire 4 ( I_A [3:0] $end
$var wire 4 ) I_B [3:0] $end
$var wire 1 & clk $end
$var wire 1 ' ctrl $end
$var wire 4 * result [3:0] $end
$var parameter 32 + bit $end
$var reg 4 , Q_next_A [3:0] $end
$var reg 4 - Q_next_B [3:0] $end
$var reg 1 . Q_next_D $end
$var reg 4 / Q_reg_A [3:0] $end
$var reg 4 0 Q_reg_B [3:0] $end
$var reg 1 1 Q_reg_D $end
$var reg 1 2 carry_out $end
$var reg 1 3 sum $end
$upscope $end
$upscope $end
$enddefinitions $end
$comment Show the parameter values. $end
$dumpall
b100 +
b100 #
b10100 "
$end
#0
$dumpvars
03
02
01
b110 0
b100 /
0.
b110 -
b100 ,
b100 *
b110 )
b100 (
0'
0&
b110 %
b100 $
b100 !
$end
#10000
b11 -
b10 ,
1'
1&
#20000
0&
#30000
b1 -
b1001 ,
13
b11 0
b10 !
b10 *
b10 /
1&
#40000
0&
#50000
b0 -
b100 ,
1.
12
03
b1 0
b1001 !
b1001 *
b1001 /
1&
#60000
0&
#70000
b1010 ,
0.
02
13
11
b0 0
b100 !
b100 *
b100 /
1&
#80000
0&
#90000
03
01
b1010 !
b1010 *
b1010 /
b111 -
b1110 ,
b111 %
b111 )
b1110 $
b1110 (
0'
1&
#100000
0&
#110000
13
b111 0
b1110 !
b1110 *
b1110 /
b11 -
b1111 ,
1'
1&
#120000
0&
#130000
b1 -
b111 ,
1.
12
03
b11 0
b1111 !
b1111 *
b1111 /
1&
#140000
0&
#150000
b0 -
b1011 ,
13
11
b1 0
b111 !
b111 *
b111 /
1&
#160000
0&
#170000
b101 ,
03
b0 0
b1011 !
b1011 *
b1011 /
1&
#180000
0&
#190000
b10 ,
b101 !
b101 *
b101 /
1&
#200000
0&
#210000
0.
02
01
b10 !
b10 *
b10 /
b110 -
b1001 ,
b110 %
b110 )
b1001 $
b1001 (
0'
1&
#220000
0&
#230000
13
b110 0
b1001 !
b1001 *
b1001 /
b11 -
b1100 ,
1'
1&
#240000
0&
#250000
b1 -
b1110 ,
b11 0
b1100 !
b1100 *
b1100 /
1&
#260000
0&
#270000
b0 -
b1111 ,
b1 0
b1110 !
b1110 *
b1110 /
1&
#280000
0&
#290000
b0 0
b1111 !
b1111 *
b1111 /
1&
