Clock Divider/clk_divider_by_n_dual_edge_ff.v

module clk_divider_by_n_dual_edge_ff 
#(parameter n = 3)
(
	input clk , rst_n ,
  output reg out_clk 
);
//Counter to count the half cylces of input clock
reg [$clog2(n):0] counter ;

always @(negedge rst_n)
begin
    out_clk <= 1'b0 ;
    counter <=  'd0 ;
end

always @(posedge clk)
begin
    //Default Values 
    out_clk <= 1'b0 ;
    counter <= 'd0 ;
    if(counter < n)
    begin
    out_clk <= 1'b1 ;
    counter <= counter + 1 ; 
    end
    else if(counter == n)
    begin
    out_clk <= 1'b0 ;
    counter <= counter + 1 ;
    end
    else if(counter < 2*n) 
    begin
    out_clk <= 1'b0 ;
    counter <= counter + 1 ;
    end
    else if(counter == 2*n)
    begin
    out_clk <= 1'b1 ;
    counter <= 'd1; 
    end
end
always @(negedge clk)
begin
    //Default Values 
    out_clk <= 1'b0 ;
    counter <= 'd0 ;
    if(counter < n)
    begin
    out_clk <= 1'b1 ;
    counter <= counter + 1 ; 
    end
    else if(counter == n)
    begin
    out_clk <= 1'b0 ;
    counter <= counter + 1 ;
    end
    else if(counter < 2*n) 
    begin
    out_clk <= 1'b0 ;
    counter <= counter + 1 ;
    end
    else if(counter == 2*n)
    begin
    out_clk <= 1'b1 ;
    counter <= 'd1; 
    end
end
// always @(posedge clk , negedge clk , negedge rst_n)
//   begin
//     //Default Values 
//     out_clk <= 1'b0 ;
//     counter <= 'd0 ;
//     if(!rst_n)
//     begin
//       out_clk <= 1'b0 ;
//       counter <=  'd0 ;
//     end
//     else 
//     begin
//       if(counter < n)
//       begin
//         out_clk <= 1'b1 ;
//         counter <= counter + 1 ; 
//       end
//       else if(counter == n)
//       begin
//         out_clk <= 1'b0 ;
//         counter <= counter + 1 ;
//       end
//       else if(counter < 2*n) 
//       begin
//         out_clk <= 1'b0 ;
//         counter <= counter + 1 ;
//       end
//       else if(counter == 2*n)
//       begin
//         out_clk <= 1'b1 ;
//         counter <= 'd1; 
//       end
//     end
//   end
endmodule

Clock Divider/clk_divider_by_n_dual_edge_ff_tb.v
`timescale 1ns / 1ns 
module clk_divider_by_n_dual_edge_ff_tb();
//declare the local , reg , and wire identifier
localparam n = 8 ;
reg clk , rst_n ;
wire out_clk ;
//Instantiate the module under test
clk_divider_by_n_dual_edge_ff #(.n(n)) uut(clk ,rst_n , out_clk);
//Counter 
integer count_high_out_clk = 0 , count_low_out_clk = 0 ;
integer count_high_clk = 0 , count_low_clk = 0 ;
//Generate the clock 
localparam T = 10 ;
always 
begin
    clk = 1'b0 ;
    #(T/2) ;
    clk = 1'b1 ;
    #(T/2) ;
end
//Initial Block to Kill the hanging 
initial 
    #100000 $finish ;
//Tasks : 
// task check;
//     integer i ;
//     begin
//         for(i=0;;i=i+1)
//     end
// endtask
//Create the stimuli using initial 
initial 
begin
    rst_n = 1'b0 ;
    #2 rst_n = 1'b1 ;
    repeat(3*n)
    begin
        @(posedge clk)
        begin
            if(clk)
                count_high_clk = count_high_clk + 1 ;
            else 
                count_low_clk = count_low_clk + 1 ;
            if(out_clk)
                count_high_out_clk = count_high_out_clk + 1 ;
            else 
                count_low_out_clk = count_low_out_clk + 1 ;
        end
        @(negedge clk)
        begin
            if(clk)
                count_high_clk = count_high_clk + 1 ;
            else 
                count_low_clk = count_low_clk + 1 ;
            if(out_clk)
                count_high_out_clk = count_high_out_clk + 1 ;
            else 
                count_low_out_clk = count_low_out_clk + 1 ;
        end
    end
    if(count_high_out_clk == count_low_out_clk)
        $display("Count_high_out_clk %d is equal to cout_low_out_clk %d " , count_high_out_clk , count_low_out_clk) ;
    else 
        $display("Count_high_out_clk %d is not equal to cout_low_out_clk %d " ,count_high_out_clk , count_low_out_clk) ;
    if(count_high_clk == count_low_clk)
        $display("Count_high_clk %d is equal to cout_low_clk %d " , count_high_clk , count_low_clk) ;
    else 
        $display("Count_high_clk %d is not equal to cout_low_clk %d " ,count_high_clk , count_low_clk) ;
    #2 $finish ;
end
initial 
begin
    $dumpfile("clk_divider_by_n_dual_edge_ff_tb.vcd");
    $dumpvars(0,clk_divider_by_n_dual_edge_ff_tb);
end
endmodule

Clock Divider/clk_divider_by_n_dual_edge_ff_tb.vcd
$date
	Fri Sep 12 08:55:48 2025
$end
$version
	Icarus Verilog
$end
$timescale
	1ns
$end
$scope module clk_divider_by_n_dual_edge_ff_tb $end
$var wire 1 ! out_clk $end
$var parameter 32 " T $end
$var parameter 32 # n $end
$var reg 1 $ clk $end
$var reg 1 % rst_n $end
$var integer 32 & count_high_clk [31:0] $end
$var integer 32 ' count_high_out_clk [31:0] $end
$var integer 32 ( count_low_clk [31:0] $end
$var integer 32 ) count_low_out_clk [31:0] $end
$scope module uut $end
$var wire 1 $ clk $end
$var wire 1 % rst_n $end
$var parameter 32 * n $end
$var reg 4 + counter [3:0] $end
$var reg 1 ! out_clk $end
$upscope $end
$upscope $end
$enddefinitions $end
$comment Show the parameter values. $end
$dumpall
b1000 *
b1000 #
b1010 "
$end
#0
$dumpvars
b0 +
b0 )
b0 (
b0 '
b0 &
0%
0$
0!
$end
#2
1%
#5
b1 +
1!
b1 )
b1 &
1$
#10
b10 +
1!
b1 '
b1 (
0$
#15
b11 +
1!
b10 '
b10 &
1$
#20
b100 +
1!
b11 '
b10 (
0$
#25
b101 +
1!
b100 '
b11 &
1$
#30
b110 +
1!
b101 '
b11 (
0$
#35
b111 +
1!
b110 '
b100 &
1$
#40
b1000 +
1!
b111 '
b100 (
0$
#45
b1001 +
0!
b1000 '
b101 &
1$
#50
b1010 +
b10 )
b101 (
0$
#55
b1011 +
b11 )
b110 &
1$
#60
b1100 +
b100 )
b110 (
0$
#65
b1101 +
b101 )
b111 &
1$
#70
b1110 +
b110 )
b111 (
0$
#75
b1111 +
b111 )
b1000 &
1$
#80
b0 +
b1000 )
b1000 (
0$
#85
b1 +
1!
b1001 )
b1001 &
1$
#90
b10 +
1!
b1001 '
b1001 (
0$
#95
b11 +
1!
b1010 '
b1010 &
1$
#100
b100 +
1!
b1011 '
b1010 (
0$
#105
b101 +
1!
b1100 '
b1011 &
1$
#110
b110 +
1!
b1101 '
b1011 (
0$
#115
b111 +
1!
b1110 '
b1100 &
1$
#120
b1000 +
1!
b1111 '
b1100 (
0$
#125
b1001 +
0!
b10000 '
b1101 &
1$
#130
b1010 +
b1010 )
b1101 (
0$
#135
b1011 +
b1011 )
b1110 &
1$
#140
b1100 +
b1100 )
b1110 (
0$
#145
b1101 +
b1101 )
b1111 &
1$
#150
b1110 +
b1110 )
b1111 (
0$
#155
b1111 +
b1111 )
b10000 &
1$
#160
b0 +
b10000 )
b10000 (
0$
#165
b1 +
1!
b10001 )
b10001 &
1$
#170
b10 +
1!
b10001 '
b10001 (
0$
#175
b11 +
1!
b10010 '
b10010 &
1$
#180
b100 +
1!
b10011 '
b10010 (
0$
#185
b101 +
1!
b10100 '
b10011 &
1$
#190
b110 +
1!
b10101 '
b10011 (
0$
#195
b111 +
1!
b10110 '
b10100 &
1$
#200
b1000 +
1!
b10111 '
b10100 (
0$
#205
b1001 +
0!
b11000 '
b10101 &
1$
#210
b1010 +
b10010 )
b10101 (
0$
#215
b1011 +
b10011 )
b10110 &
1$
#220
b1100 +
b10100 )
b10110 (
0$
#225
b1101 +
b10101 )
b10111 &
1$
#230
b1110 +
b10110 )
b10111 (
0$
#235
b1111 +
b10111 )
b11000 &
1$
#240
b0 +
b11000 )
b11000 (
0$
