Fibonacci number circuit/fib.v
`timescale 1ns / 1ps 
module fib(
    input clk , reset_n , start ,
    input [4:0]i, // for input iterations need
    output [19:0]f, // Output 
    output reg ready , done_tick
);
//Storage Elements

reg [1:0]state_reg , state_next ;
reg [19:0]t1_reg ,t1_next , t0_reg , t0_next ;
reg [4:0]n_reg , n_next ; 

localparam idle = 2'b00 , op = 2'b01 ,done = 2'b10 ;

always @(posedge clk,negedge reset_n)
begin
    if(!reset_n)
    begin
        state_reg <= idle ;
        t1_reg <= 'd1 ;
        t0_reg <= 'd0 ;
        n_reg <= 'd0 ;
    end
    else 
    begin
        state_reg <= state_next ;
        t1_reg <= t1_next ;
        t0_reg <= t0_next ;
        n_reg <= n_next ;
    end
end
//Next state Logic 
always @(*)
begin
    //Default Values 
    state_next = state_reg;
    t1_next = t1_reg ;
    t0_next = t0_reg ;
    n_next = n_reg ;
    ready = 1'b0 ;
    done_tick = 1'b0 ;
    case(state_reg)
        idle:
        begin
            ready = 1'b1 ;
            if(start == 1)
            begin
                t0_next = 'd0 ;
                t1_next = 'd1 ;
                n_next = i ;
                state_next = op ;
            end
        end
        op:
        begin
            if(n_reg == 0)
            begin
                t1_next = 'd0 ;
                state_next = done ;
            end
            else if(n_reg == 1)
            begin
                state_next = done ;
            end
            else 
            begin
                t1_next = t1_reg + t0_reg ;
                t0_next = t1_reg ;
                n_next = n_reg - 1 ;
                state_next = op ;
            end
        end
        done :
        begin
            done_tick = 1'b1 ;
            state_next = idle ;
        end
        default : state_next = idle ;
    endcase

end
//Output Logic
assign f = t1_reg ;
endmodule

Fibonacci number circuit/fib_tb.v
`timescale 1ns / 1ps 
module fib_tb();
//declare the local , reg , and wire identifiers
reg clk ,reset_n ,start ;
reg [4:0]i;
wire [19:0]f;
wire ready , done_tick ;
//Instantiate the module under test
fib uut(
    .clk(clk),
    .reset_n(reset_n),
    .start(start),
    .i(i),
    .f(f),
    .ready(ready),
    .done_tick(done_tick)
); 
//Generate the clock 
localparam T = 10 ;
always 
begin
    clk = 1'b0 ;
    #(T/2);
    clk = 1'b1 ;
    #(T/2);
end
//create the waveforms file 
initial 
begin
    $dumpfile("fib_tb.vcd");
    $dumpvars(0,fib_tb);
end
//Create the stimulus using initial and always keyword
initial 
begin
    reset_n = 1'b0 ;
    #2 reset_n = 1'b1 ;
    i = 'd9 ;
    start = 1'b1 ;
    wait(done_tick);
    i = 'd4;
    repeat(2) @(posedge clk);
    wait(done_tick) ;
    #T $finish;
end
endmodule

Fibonacci number circuit/fib_tb.vcd
$date
	Tue Jul 22 20:50:58 2025
$end
$version
	Icarus Verilog
$end
$timescale
	1ps
$end
$scope module fib_tb $end
$var wire 1 ! ready $end
$var wire 20 " f [19:0] $end
$var wire 1 # done_tick $end
$var parameter 32 $ T $end
$var reg 1 % clk $end
$var reg 5 & i [4:0] $end
$var reg 1 ' reset_n $end
$var reg 1 ( start $end
$scope module uut $end
$var wire 1 % clk $end
$var wire 20 ) f [19:0] $end
$var wire 5 * i [4:0] $end
$var wire 1 ' reset_n $end
$var wire 1 ( start $end
$var parameter 2 + done $end
$var parameter 2 , idle $end
$var parameter 2 - op $end
$var reg 1 # done_tick $end
$var reg 5 . n_next [4:0] $end
$var reg 5 / n_reg [4:0] $end
$var reg 1 ! ready $end
$var reg 2 0 state_next [1:0] $end
$var reg 2 1 state_reg [1:0] $end
$var reg 20 2 t0_next [19:0] $end
$var reg 20 3 t0_reg [19:0] $end
$var reg 20 4 t1_next [19:0] $end
$var reg 20 5 t1_reg [19:0] $end
$upscope $end
$upscope $end
$enddefinitions $end
$comment Show the parameter values. $end
$dumpall
b1 -
b0 ,
b10 +
b1010 $
$end
#0
$dumpvars
b1 5
b1 4
b0 3
b0 2
b0 1
b0 0
b0 /
b0 .
bx *
b1 )
x(
0'
bx &
0%
0#
b1 "
1!
$end
#2000
b1 0
b1001 .
1!
1(
b1001 &
b1001 *
1'
#5000
b1000 .
b1 2
0!
b1001 /
b1 1
1%
#10000
0%
#15000
b111 .
b10 4
b1000 /
b1 3
1%
#20000
0%
#25000
b110 .
b10 2
b11 4
b111 /
b10 "
b10 )
b10 5
1%
#30000
0%
#35000
b101 .
b11 2
b101 4
b110 /
b10 3
b11 "
b11 )
b11 5
1%
#40000
0%
#45000
b100 .
b101 2
b1000 4
b101 /
b11 3
b101 "
b101 )
b101 5
1%
#50000
0%
#55000
b11 .
b1000 2
b1101 4
b100 /
b101 3
b1000 "
b1000 )
b1000 5
1%
#60000
0%
#65000
b10 .
b1101 2
b10101 4
b11 /
b1000 3
b1101 "
b1101 )
b1101 5
1%
#70000
0%
#75000
b1 .
b10101 2
b100010 4
b10 /
b1101 3
b10101 "
b10101 )
b10101 5
1%
#80000
0%
#85000
b10 0
b1 /
b10101 3
b100010 "
b100010 )
b100010 5
1%
#90000
0%
#95000
b100 &
b100 *
b0 0
1#
b10 1
1%
#100000
0%
#105000
b1 0
b100 .
b1 4
b0 2
1!
0#
b0 1
1%
#110000
0%
#115000
b11 .
b1 2
0!
b100 /
b0 3
b1 "
b1 )
b1 5
b1 1
1%
#120000
0%
#125000
b10 .
b10 4
b11 /
b1 3
1%
#130000
0%
#135000
b1 .
b10 2
b11 4
b10 /
b10 "
b10 )
b10 5
1%
#140000
0%
#145000
b10 0
b1 /
b10 3
b11 "
b11 )
b11 5
1%
#150000
0%
#155000
b0 0
1#
b10 1
1%
#160000
0%
#165000
b1 0
b100 .
b1 4
b0 2
1!
0#
b0 1
1%
